exciton/__init__.py
exciton/ml/__init__.py
exciton/ml/classification/__init__.py
exciton/ml/classification/bert/__init__.py
exciton/ml/classification/bert/model.py
exciton/ml/classification/bert/trainer.py
exciton/ml/classification/bert/utils.py
exciton/ml/engine/__init__.py
exciton/ml/engine/end2end.py
exciton/ml/engine/utils.py
exciton/ml/tagging/__init__.py
exciton/ml/tagging/utils.py
exciton/ml/tagging/bert/__init__.py
exciton/ml/tagging/bert/model.py
exciton/ml/tagging/bert/trainer.py
exciton/nlp/__init__.py
exciton/nlp/company_clean/__init__.py
exciton/nlp/company_clean/cleanco.py
exciton/nlp/event_detection/__init__.py
exciton/nlp/event_detection/bert.py
exciton/nlp/event_detection/utils.py
exciton/nlp/keywords_extraction/__init__.py
exciton/nlp/keywords_extraction/flashtext.py
exciton/nlp/lang_detection/__init__.py
exciton/nlp/lang_detection/exciton_detection.py
exciton/nlp/llm_chat/__init__.py
exciton/nlp/llm_chat/chat_v0.py
exciton/nlp/llm_chat/chat_v1.py
exciton/nlp/llm_chat/service.py
exciton/nlp/named_entity_recognition/__init__.py
exciton/nlp/named_entity_recognition/exciton.py
exciton/nlp/named_entity_recognition/pretrain.py
exciton/nlp/named_entity_recognition/utils.py
exciton/nlp/sentence_tokenizer/__init__.py
exciton/nlp/sentence_tokenizer/exciton_sbd.py
exciton/nlp/sentiment_analysis/__init__.py
exciton/nlp/sentiment_analysis/finbert.py
exciton/nlp/text_matching/__init__.py
exciton/nlp/text_matching/exciton_matching.py
exciton/nlp/topic_relevance/__init__.py
exciton/nlp/topic_relevance/exciton_relevance.py
exciton/nlp/translation/__init__.py
exciton/nlp/translation/m2m100/__init__.py
exciton/nlp/translation/m2m100/service.py
exciton-2.9.3.dist-info/LICENSE
exciton-2.9.3.dist-info/METADATA
exciton-2.9.3.dist-info/WHEEL
exciton-2.9.3.dist-info/top_level.txt
exciton-2.9.3.dist-info/RECORD
