Metadata-Version: 2.1
Name: exciton
Version: 2.9.3
Summary: Natural Language Processing by the Exciton Research
Home-page: https://excitonresearch.com
Author: The Exciton Research Team
Author-email: excitonresearch@gmail.com
License: UNKNOWN
Keywords: NLP Deep Learning
Platform: UNKNOWN
Classifier: Intended Audience :: Science/Research
Classifier: Development Status :: 3 - Alpha
Classifier: License :: OSI Approved :: Apache Software License
Classifier: Programming Language :: Python :: 3
Classifier: Topic :: Scientific/Engineering :: Artificial Intelligence
Requires-Python: >=3.8
License-File: LICENSE
Requires-Dist: accelerate (==0.29.2)
Requires-Dist: auto-gptq (==0.7.1)
Requires-Dist: ctranslate2 (==3.11.0)
Requires-Dist: numpy (==1.24.2)
Requires-Dist: optimum (==1.16.0)
Requires-Dist: pysbd (==0.3.4)
Requires-Dist: scikit-learn (==1.2.2)
Requires-Dist: sentence-splitter (==1.4)
Requires-Dist: sentencepiece (==0.1.98)
Requires-Dist: spacy (==3.5.2)
Requires-Dist: torch (==2.2.2)
Requires-Dist: tqdm (==4.65.0)
Requires-Dist: transformers (==4.39.3)
